AUTHORS.rst
CONTRIBUTING.rst
HISTORY.rst
LICENSE
MANIFEST.in
README.rst
setup.cfg
setup.py
docs/Makefile
docs/authors.rst
docs/conf.py
docs/contributing.rst
docs/history.rst
docs/index.rst
docs/installation.rst
docs/make.bat
docs/readme.rst
docs/usage.rst
pic2slide/__init__.py
pic2slide/cli.py
pic2slide/pic2slide.py
pic2slide.egg-info/PKG-INFO
pic2slide.egg-info/SOURCES.txt
pic2slide.egg-info/dependency_links.txt
pic2slide.egg-info/entry_points.txt
pic2slide.egg-info/not-zip-safe
pic2slide.egg-info/requires.txt
pic2slide.egg-info/top_level.txt
tests/__init__.py
tests/test_pic2slide.py