Metadata-Version: 1.1
Name: pic2slide
Version: 0.1.0
Summary: Tools can convert pictures collection to slide.
Home-page: https://github.com/renweibo/pic2slide
Author: Weibo Ren
Author-email: renweibo@gmail.com
License: MIT license
Keywords: pic2slide
Platform: UNKNOWN
Classifier: Development Status :: 2 - Pre-Alpha
Classifier: Intended Audience :: Developers
Classifier: License :: OSI Approved :: MIT License
Classifier: Natural Language :: English
Classifier: Programming Language :: Python :: 2
Classifier: Programming Language :: Python :: 2.6
Classifier: Programming Language :: Python :: 2.7
Classifier: Programming Language :: Python :: 3
Classifier: Programming Language :: Python :: 3.3
Classifier: Programming Language :: Python :: 3.4
Classifier: Programming Language :: Python :: 3.5
Classifier: Programming Language :: Python :: 3.6
